{
    "name": "landmark in country",
    "prompt_templates": [
        "{} is in the country of"
    ],
    "prompt_templates_zs": [
        "What country is {} in? It is in",
        "{} is in the country of"
    ],
    "properties": {
        "relation_type": "factual",
        "domain_name": "landmark",
        "range_name": "country",
        "symmetric": false
    },
    "samples": [
        {
            "subject": "Autonomous University of Madrid",
            "object": "Spain"
        },
        {
            "subject": "Pochepsky District",
            "object": "Russia"
        },
        {
            "subject": "Kuala Langat",
            "object": "Malaysia"
        },
        {
            "subject": "Wanne-Eickel Central Station",
            "object": "Germany"
        },
        {
            "subject": "Hohenlohe-Langenburg",
            "object": "Germany"
        },
        {
            "subject": "Bastille",
            "object": "France"
        },
        {
            "subject": "Shablykinsky District",
            "object": "Russia"
        },
        {
            "subject": "Manila Light Rail Transit System",
            "object": "Philippines"
        },
        {
            "subject": "Valdemarsvik",
            "object": "Sweden"
        },
        {
            "subject": "Ozumba",
            "object": "Mexico"
        },
        {
            "subject": "Piper Verlag",
            "object": "Germany"
        },
        {
            "subject": "Attingal",
            "object": "India"
        },
        {
            "subject": "Georgians",
            "object": "Azerbaijan"
        },
        {
            "subject": "Nizampatnam",
            "object": "India"
        },
        {
            "subject": "Tehri Garhwal district",
            "object": "India"
        },
        {
            "subject": "Eirodziesma",
            "object": "Latvia"
        },
        {
            "subject": "Olot",
            "object": "Spain"
        },
        {
            "subject": "Sumulong Highway",
            "object": "Philippines"
        },
        {
            "subject": "Darmstadt",
            "object": "Germany"
        },
        {
            "subject": "Adliswil",
            "object": "Switzerland"
        },
        {
            "subject": "Junnar",
            "object": "India"
        },
        {
            "subject": "Ba F.C.",
            "object": "Fiji"
        },
        {
            "subject": "Kandiaro Taluka",
            "object": "Pakistan"
        },
        {
            "subject": "Yoro",
            "object": "Honduras"
        },
        {
            "subject": "Queen Charlotte Mountains",
            "object": "Canada"
        },
        {
            "subject": "Knockmealdown Mountains",
            "object": "Ireland"
        },
        {
            "subject": "Calw",
            "object": "Germany"
        },
        {
            "subject": "Gazzola",
            "object": "Italy"
        },
        {
            "subject": "1960 Summer Olympics",
            "object": "Italy"
        },
        {
            "subject": "Borovsky District",
            "object": "Russia"
        },
        {
            "subject": "Eibenstock",
            "object": "Germany"
        },
        {
            "subject": "Kyoto University",
            "object": "Japan"
        },
        {
            "subject": "Bay",
            "object": "Philippines"
        },
        {
            "subject": "Medaram",
            "object": "India"
        },
        {
            "subject": "Chu Lai Base Area",
            "object": "Vietnam"
        },
        {
            "subject": "Kosi Zone",
            "object": "Nepal"
        },
        {
            "subject": "National Highway 45",
            "object": "India"
        },
        {
            "subject": "Kfar Giladi",
            "object": "Israel"
        },
        {
            "subject": "Mandara Mountains",
            "object": "Nigeria"
        },
        {
            "subject": "Agios Dimitrios",
            "object": "Greece"
        },
        {
            "subject": "Vijayawada Junction railway station",
            "object": "India"
        },
        {
            "subject": "Allersberg",
            "object": "Germany"
        },
        {
            "subject": "Noliko Maaseik",
            "object": "Belgium"
        },
        {
            "subject": "Imsland",
            "object": "Norway"
        },
        {
            "subject": "Dwarka",
            "object": "India"
        },
        {
            "subject": "Hultsfred Municipality",
            "object": "Sweden"
        },
        {
            "subject": "Hattfjelldal",
            "object": "Norway"
        },
        {
            "subject": "Dent Island Light",
            "object": "Australia"
        },
        {
            "subject": "Al Daayen",
            "object": "Qatar"
        },
        {
            "subject": "Hurley River",
            "object": "Canada"
        },
        {
            "subject": "Pontecorvo",
            "object": "Italy"
        },
        {
            "subject": "Ustevatn",
            "object": "Norway"
        },
        {
            "subject": "Acolman Municipality",
            "object": "Mexico"
        },
        {
            "subject": "Astrid Lindgren Memorial Award",
            "object": "Sweden"
        },
        {
            "subject": "Liverpool Range",
            "object": "Australia"
        },
        {
            "subject": "Nova Friburgo",
            "object": "Brazil"
        },
        {
            "subject": "Sydney Peace Prize",
            "object": "Australia"
        },
        {
            "subject": "Sarpsborg 08 FF",
            "object": "Norway"
        },
        {
            "subject": "Jan Amora",
            "object": "Ethiopia"
        },
        {
            "subject": "Christian Medical College Ludhiana",
            "object": "India"
        },
        {
            "subject": "Yokohama International School",
            "object": "Japan"
        },
        {
            "subject": "KiKa",
            "object": "Germany"
        },
        {
            "subject": "Canjuers",
            "object": "France"
        },
        {
            "subject": "Giurgiu County",
            "object": "Romania"
        },
        {
            "subject": "La Mauricie National Park",
            "object": "Canada"
        },
        {
            "subject": "Ballydehob",
            "object": "Ireland"
        },
        {
            "subject": "Maybach",
            "object": "Germany"
        },
        {
            "subject": "Rankuh District",
            "object": "Iran"
        },
        {
            "subject": "Khasavyurt",
            "object": "Russia"
        },
        {
            "subject": "Capolago",
            "object": "Switzerland"
        },
        {
            "subject": "Ateneo de Madrid",
            "object": "Spain"
        },
        {
            "subject": "Toronto Police Service",
            "object": "Canada"
        },
        {
            "subject": "Pilis Mountains",
            "object": "Hungary"
        },
        {
            "subject": "Ginza",
            "object": "Japan"
        },
        {
            "subject": "Lake Caliraya",
            "object": "Philippines"
        },
        {
            "subject": "Skinnamarink TV",
            "object": "Canada"
        },
        {
            "subject": "2004 Indian Ocean earthquake",
            "object": "Indonesia"
        },
        {
            "subject": "agglomeration community",
            "object": "France"
        },
        {
            "subject": "Carpentras",
            "object": "France"
        },
        {
            "subject": "Neryungri",
            "object": "Russia"
        },
        {
            "subject": "New England",
            "object": "Australia"
        },
        {
            "subject": "Lower Assam",
            "object": "India"
        },
        {
            "subject": "Bad Vilbel",
            "object": "Germany"
        },
        {
            "subject": "Dawa River",
            "object": "Somalia"
        },
        {
            "subject": "Kayunga District",
            "object": "Uganda"
        },
        {
            "subject": "Hellenic Police",
            "object": "Greece"
        },
        {
            "subject": "Kamikita District",
            "object": "Japan"
        },
        {
            "subject": "Ayn Halaqim Subdistrict",
            "object": "Syria"
        },
        {
            "subject": "Club Aurora",
            "object": "Bolivia"
        },
        {
            "subject": "Clonlara GAA",
            "object": "Ireland"
        },
        {
            "subject": "Bobolice",
            "object": "Poland"
        },
        {
            "subject": "Barnhartvale, Kamloops",
            "object": "Canada"
        },
        {
            "subject": "Norfolk Air",
            "object": "Australia"
        },
        {
            "subject": "Sakarya Province",
            "object": "Turkey"
        },
        {
            "subject": "Zwiefalten",
            "object": "Germany"
        },
        {
            "subject": "Narman",
            "object": "Turkey"
        },
        {
            "subject": "Bliesgau",
            "object": "Germany"
        },
        {
            "subject": "Inami, Toyama",
            "object": "Japan"
        },
        {
            "subject": "Iximche",
            "object": "Guatemala"
        },
        {
            "subject": "Thuringian Highland",
            "object": "Germany"
        },
        {
            "subject": "Mudgee",
            "object": "Australia"
        },
        {
            "subject": "Bernheze",
            "object": "Netherlands"
        },
        {
            "subject": "Tursi",
            "object": "Italy"
        },
        {
            "subject": "Reiherstieg Schiffswerfte & Maschinenfabrik",
            "object": "Germany"
        },
        {
            "subject": "Kalvola",
            "object": "Finland"
        },
        {
            "subject": "Registro",
            "object": "Brazil"
        },
        {
            "subject": "East Wall",
            "object": "Ireland"
        },
        {
            "subject": "Augusta Raurica",
            "object": "Switzerland"
        },
        {
            "subject": "Bilbao",
            "object": "Spain"
        },
        {
            "subject": "Sarnaki",
            "object": "Poland"
        },
        {
            "subject": "Peremyshliany",
            "object": "Ukraine"
        },
        {
            "subject": "Bilohirsk Raion",
            "object": "Russia"
        },
        {
            "subject": "Etobicoke North",
            "object": "Canada"
        },
        {
            "subject": "Singel",
            "object": "Netherlands"
        },
        {
            "subject": "Lund Municipality",
            "object": "Sweden"
        },
        {
            "subject": "Borgo San Martino",
            "object": "Italy"
        },
        {
            "subject": "Moi International Sports Centre",
            "object": "Kenya"
        },
        {
            "subject": "Garibaldi Ranges",
            "object": "Canada"
        },
        {
            "subject": "Hong San See",
            "object": "Singapore"
        },
        {
            "subject": "Lucentum",
            "object": "Spain"
        },
        {
            "subject": "Dumka district",
            "object": "India"
        },
        {
            "subject": "Amsterdam dance event",
            "object": "Netherlands"
        },
        {
            "subject": "Dospat Municipality",
            "object": "Bulgaria"
        },
        {
            "subject": "Eredivisie",
            "object": "Netherlands"
        },
        {
            "subject": "Subarnapur district",
            "object": "India"
        },
        {
            "subject": "Kennedy Highway",
            "object": "Australia"
        },
        {
            "subject": "Pannonhalma Archabbey",
            "object": "Hungary"
        },
        {
            "subject": "Banesh Rural District",
            "object": "Iran"
        },
        {
            "subject": "Broken Pencil",
            "object": "Canada"
        },
        {
            "subject": "Sydney Hospital",
            "object": "Australia"
        },
        {
            "subject": "Cork GAA",
            "object": "Ireland"
        },
        {
            "subject": "Hohenwestedt",
            "object": "Germany"
        },
        {
            "subject": "Buraswa",
            "object": "India"
        },
        {
            "subject": "Kibungo Province",
            "object": "Rwanda"
        },
        {
            "subject": "Harnaut",
            "object": "India"
        },
        {
            "subject": "Westerburg",
            "object": "Germany"
        },
        {
            "subject": "Zulia",
            "object": "Venezuela"
        },
        {
            "subject": "Virgin Classics",
            "object": "France"
        },
        {
            "subject": "People's Party for Freedom and Democracy",
            "object": "Netherlands"
        },
        {
            "subject": "DESTATIS",
            "object": "Germany"
        },
        {
            "subject": "Imperia",
            "object": "Italy"
        },
        {
            "subject": "Gammalsvenskby",
            "object": "Ukraine"
        },
        {
            "subject": "Menangle Park",
            "object": "Australia"
        },
        {
            "subject": "Kungliga Svenska Segels\u00e4llskapet",
            "object": "Sweden"
        },
        {
            "subject": "Drumheller-Stettler",
            "object": "Canada"
        },
        {
            "subject": "Markham District High School",
            "object": "Canada"
        },
        {
            "subject": "Isa Air Base",
            "object": "Bahrain"
        },
        {
            "subject": "Palais de l'Industrie",
            "object": "France"
        },
        {
            "subject": "Le Puy Foot 43 Auvergne",
            "object": "France"
        },
        {
            "subject": "Medical College and Hospital, Kolkata",
            "object": "India"
        },
        {
            "subject": "Kahrizak",
            "object": "Iran"
        },
        {
            "subject": "Bouygues Telecom",
            "object": "France"
        },
        {
            "subject": "Second Rutte cabinet",
            "object": "Netherlands"
        },
        {
            "subject": "Mahalangur Himal",
            "object": "Nepal"
        },
        {
            "subject": "Delta Works",
            "object": "Netherlands"
        },
        {
            "subject": "Davan",
            "object": "Iran"
        },
        {
            "subject": "Munich Residence",
            "object": "Germany"
        },
        {
            "subject": "Marugame",
            "object": "Japan"
        },
        {
            "subject": "Lutvann",
            "object": "Norway"
        },
        {
            "subject": "Pesisir Selatan",
            "object": "Indonesia"
        },
        {
            "subject": "Alfred Wegener Institute for Polar and Marine Research",
            "object": "Germany"
        },
        {
            "subject": "Lismore GAA",
            "object": "Ireland"
        },
        {
            "subject": "TUIfly Nordic",
            "object": "Sweden"
        },
        {
            "subject": "Pakpattan",
            "object": "Pakistan"
        },
        {
            "subject": "Kanchanaburi",
            "object": "Thailand"
        },
        {
            "subject": "Lleida",
            "object": "Spain"
        },
        {
            "subject": "Leap Castle",
            "object": "Ireland"
        },
        {
            "subject": "Mediolanum Forum",
            "object": "Italy"
        },
        {
            "subject": "Saint-Jacques-de-la-Lande",
            "object": "France"
        },
        {
            "subject": "Ankenes",
            "object": "Norway"
        },
        {
            "subject": "Hyderabad Deccan railway station",
            "object": "India"
        },
        {
            "subject": "Higashikagawa",
            "object": "Japan"
        },
        {
            "subject": "Sun News Network",
            "object": "Canada"
        },
        {
            "subject": "Mirbag-e Shomali Rural District",
            "object": "Iran"
        },
        {
            "subject": "Amos Anderson Art Museum",
            "object": "Finland"
        },
        {
            "subject": "Cocconato",
            "object": "Italy"
        },
        {
            "subject": "Al-Suqaylabiyah Subdistrict",
            "object": "Syria"
        },
        {
            "subject": "Arve",
            "object": "France"
        },
        {
            "subject": "Idalium",
            "object": "Cyprus"
        },
        {
            "subject": "Nuri",
            "object": "Sudan"
        },
        {
            "subject": "Pontigny Abbey",
            "object": "France"
        },
        {
            "subject": "Kununurra",
            "object": "Australia"
        },
        {
            "subject": "JVC Kenwood Victor Entertainment",
            "object": "Japan"
        },
        {
            "subject": "Augustdorf",
            "object": "Germany"
        },
        {
            "subject": "Kaniv Reservoir",
            "object": "Ukraine"
        },
        {
            "subject": "VTB Capital",
            "object": "Russia"
        },
        {
            "subject": "Hardoi district",
            "object": "India"
        },
        {
            "subject": "Trento",
            "object": "Italy"
        },
        {
            "subject": "Kadrina Rural Municipality",
            "object": "Estonia"
        },
        {
            "subject": "Alberta Alliance Party",
            "object": "Canada"
        },
        {
            "subject": "Valhalla Swimming Hall",
            "object": "Sweden"
        },
        {
            "subject": "Sidhi district",
            "object": "India"
        },
        {
            "subject": "Santo Stefano d'Aveto",
            "object": "Italy"
        },
        {
            "subject": "Colleville-Montgomery",
            "object": "France"
        },
        {
            "subject": "Heptapyrgion",
            "object": "Greece"
        },
        {
            "subject": "Sena Medal",
            "object": "India"
        },
        {
            "subject": "Piove di Sacco",
            "object": "Italy"
        },
        {
            "subject": "Bird's Head Peninsula",
            "object": "Indonesia"
        },
        {
            "subject": "Elgin West",
            "object": "Canada"
        },
        {
            "subject": "Bahujan Vikas Aaghadi",
            "object": "India"
        },
        {
            "subject": "Global Television Network",
            "object": "Canada"
        },
        {
            "subject": "IL Brodd",
            "object": "Norway"
        },
        {
            "subject": "Ticho House",
            "object": "Israel"
        },
        {
            "subject": "Sommariva del Bosco",
            "object": "Italy"
        },
        {
            "subject": "Grobbendonk",
            "object": "Belgium"
        },
        {
            "subject": "House of Representatives",
            "object": "Libya"
        },
        {
            "subject": "Ust-Katav",
            "object": "Russia"
        },
        {
            "subject": "Stentoften Runestone",
            "object": "Sweden"
        },
        {
            "subject": "Alte Nationalgalerie",
            "object": "Germany"
        },
        {
            "subject": "Jafara",
            "object": "Libya"
        },
        {
            "subject": "Union des forces progressistes",
            "object": "Canada"
        },
        {
            "subject": "Ljig",
            "object": "Serbia"
        },
        {
            "subject": "Nizhneserginsky District",
            "object": "Russia"
        },
        {
            "subject": "Vierlingsbeek",
            "object": "Netherlands"
        },
        {
            "subject": "Ferrobaires",
            "object": "Argentina"
        },
        {
            "subject": "Bugis Junction",
            "object": "Singapore"
        },
        {
            "subject": "Were Ilu",
            "object": "Ethiopia"
        },
        {
            "subject": "San Canzian d'Isonzo",
            "object": "Italy"
        },
        {
            "subject": "Stara Zagora",
            "object": "Bulgaria"
        },
        {
            "subject": "Polish Football Association",
            "object": "Poland"
        },
        {
            "subject": "Simeulue",
            "object": "Indonesia"
        },
        {
            "subject": "Tinguiririca River",
            "object": "Chile"
        },
        {
            "subject": "Aucanquilcha",
            "object": "Chile"
        },
        {
            "subject": "Cayeux-sur-Mer",
            "object": "France"
        },
        {
            "subject": "Mittag-Leffler Institute",
            "object": "Sweden"
        },
        {
            "subject": "National Republican Greek League",
            "object": "Greece"
        },
        {
            "subject": "Indus River",
            "object": "India"
        },
        {
            "subject": "Lindholm station",
            "object": "Denmark"
        },
        {
            "subject": "Gmina Bodzentyn",
            "object": "Poland"
        },
        {
            "subject": "Federally Administered Tribal Areas",
            "object": "Pakistan"
        },
        {
            "subject": "Guldborg",
            "object": "Denmark"
        },
        {
            "subject": "Papantla",
            "object": "Mexico"
        },
        {
            "subject": "Kottarakkara",
            "object": "India"
        },
        {
            "subject": "Risod",
            "object": "India"
        },
        {
            "subject": "Ky\u014dto Prefecture",
            "object": "Japan"
        },
        {
            "subject": "Helsinki City Hall",
            "object": "Finland"
        },
        {
            "subject": "Bad Schwalbach",
            "object": "Germany"
        },
        {
            "subject": "Uromi",
            "object": "Nigeria"
        },
        {
            "subject": "Lambunao",
            "object": "Philippines"
        },
        {
            "subject": "Circuito da Boavista",
            "object": "Portugal"
        },
        {
            "subject": "Bhamdoun",
            "object": "Lebanon"
        },
        {
            "subject": "FC Gorodeya",
            "object": "Belarus"
        },
        {
            "subject": "Loppa",
            "object": "Norway"
        },
        {
            "subject": "Trigono",
            "object": "Greece"
        },
        {
            "subject": "Entzheim",
            "object": "France"
        },
        {
            "subject": "Trans-Sahara Highway",
            "object": "Nigeria"
        },
        {
            "subject": "Umarex",
            "object": "Germany"
        },
        {
            "subject": "Cunter",
            "object": "Switzerland"
        },
        {
            "subject": "Tarn-et-Garonne",
            "object": "France"
        },
        {
            "subject": "Gavrilovo-Posadsky District",
            "object": "Russia"
        },
        {
            "subject": "Bangarapet",
            "object": "India"
        },
        {
            "subject": "Tinapa Resort",
            "object": "Nigeria"
        },
        {
            "subject": "Roman Catholic Archdiocese of Ljubljana",
            "object": "Slovenia"
        },
        {
            "subject": "Maya River",
            "object": "Russia"
        },
        {
            "subject": "Media Development Authority",
            "object": "Singapore"
        },
        {
            "subject": "Zbuczyn",
            "object": "Poland"
        },
        {
            "subject": "Roman Catholic Archdiocese of Lucca",
            "object": "Italy"
        },
        {
            "subject": "Inuit Circumpolar Council",
            "object": "Canada"
        },
        {
            "subject": "Bannu",
            "object": "Pakistan"
        },
        {
            "subject": "Zaraysky District",
            "object": "Russia"
        },
        {
            "subject": "Tienen",
            "object": "Belgium"
        },
        {
            "subject": "Camarate",
            "object": "Portugal"
        },
        {
            "subject": "Karimnagar district",
            "object": "India"
        },
        {
            "subject": "Guillaumes",
            "object": "France"
        },
        {
            "subject": "Rottumerplaat",
            "object": "Netherlands"
        },
        {
            "subject": "Art Gallery of Ontario",
            "object": "Canada"
        },
        {
            "subject": "Hooge Crater Commonwealth War Graves Commission Cemetery",
            "object": "Belgium"
        },
        {
            "subject": "Taksim Military Barracks",
            "object": "Turkey"
        },
        {
            "subject": "United Mine Workers",
            "object": "Canada"
        },
        {
            "subject": "Huachocolpa District",
            "object": "Peru"
        },
        {
            "subject": "Goseck circle",
            "object": "Germany"
        },
        {
            "subject": "Aden",
            "object": "Yemen"
        },
        {
            "subject": "South East Forests National Park",
            "object": "Australia"
        },
        {
            "subject": "Kaunas Cathedral Basilica",
            "object": "Lithuania"
        },
        {
            "subject": "Rantum",
            "object": "Germany"
        },
        {
            "subject": "Weston GO Station",
            "object": "Canada"
        },
        {
            "subject": "Al-Hasakah Governorate",
            "object": "Syria"
        },
        {
            "subject": "Amarkantak",
            "object": "India"
        },
        {
            "subject": "Manila Bay",
            "object": "Philippines"
        },
        {
            "subject": "Blackrock Castle",
            "object": "Ireland"
        },
        {
            "subject": "Beauvais",
            "object": "France"
        },
        {
            "subject": "Oseberg oil field",
            "object": "Norway"
        },
        {
            "subject": "Gavork-e Nalin Rural District",
            "object": "Iran"
        },
        {
            "subject": "European route E25",
            "object": "Luxembourg"
        },
        {
            "subject": "cadastral municipality",
            "object": "Netherlands"
        },
        {
            "subject": "Gmina Stara Kornica",
            "object": "Poland"
        },
        {
            "subject": "Annweiler am Trifels",
            "object": "Germany"
        },
        {
            "subject": "Circuit des Ardennes",
            "object": "Belgium"
        },
        {
            "subject": "Konark Sun temple",
            "object": "India"
        },
        {
            "subject": "County Leitrim",
            "object": "Ireland"
        },
        {
            "subject": "Gmina Kalinowo",
            "object": "Poland"
        },
        {
            "subject": "Da Nang Air Base",
            "object": "Vietnam"
        },
        {
            "subject": "Arsk",
            "object": "Russia"
        },
        {
            "subject": "Arjoun",
            "object": "Syria"
        },
        {
            "subject": "Bjurholm",
            "object": "Sweden"
        },
        {
            "subject": "E.ON Sverige",
            "object": "Sweden"
        },
        {
            "subject": "Veyrier",
            "object": "Switzerland"
        },
        {
            "subject": "Pindamonhangaba",
            "object": "Brazil"
        },
        {
            "subject": "Bad Camberg",
            "object": "Germany"
        },
        {
            "subject": "Colegio Nacional de Buenos Aires",
            "object": "Argentina"
        },
        {
            "subject": "Montemitro",
            "object": "Italy"
        },
        {
            "subject": "Ikaalinen",
            "object": "Finland"
        },
        {
            "subject": "CD Eldense",
            "object": "Spain"
        },
        {
            "subject": "Rio Quente",
            "object": "Brazil"
        },
        {
            "subject": "Wismar",
            "object": "Germany"
        },
        {
            "subject": "Naruto Strait",
            "object": "Japan"
        },
        {
            "subject": "ABC Futebol Clube",
            "object": "Brazil"
        },
        {
            "subject": "Waalhaven",
            "object": "Netherlands"
        },
        {
            "subject": "Atwell Peak",
            "object": "Canada"
        },
        {
            "subject": "Sadr City",
            "object": "Iraq"
        },
        {
            "subject": "Palladam",
            "object": "India"
        },
        {
            "subject": "Orpheus Island National Park",
            "object": "Australia"
        },
        {
            "subject": "Achelous River",
            "object": "Greece"
        },
        {
            "subject": "FC Anker Wismar",
            "object": "Germany"
        },
        {
            "subject": "Sapo National Park",
            "object": "Liberia"
        },
        {
            "subject": "Poissy",
            "object": "France"
        },
        {
            "subject": "Eagle Boys",
            "object": "Australia"
        },
        {
            "subject": "Shichikashuku",
            "object": "Japan"
        },
        {
            "subject": "Bhinmal",
            "object": "India"
        },
        {
            "subject": "Bourg-la-Reine",
            "object": "France"
        },
        {
            "subject": "Nagoya University",
            "object": "Japan"
        },
        {
            "subject": "Minamishitara District, Aichi",
            "object": "Japan"
        },
        {
            "subject": "Coolock",
            "object": "Ireland"
        },
        {
            "subject": "Shakhenat Rural District",
            "object": "Iran"
        },
        {
            "subject": "Soalala",
            "object": "Madagascar"
        },
        {
            "subject": "Gmina Leszno",
            "object": "Poland"
        },
        {
            "subject": "Battle of Montereau",
            "object": "France"
        },
        {
            "subject": "Theni district",
            "object": "India"
        },
        {
            "subject": "Galiano Island",
            "object": "Canada"
        },
        {
            "subject": "Kluuvi",
            "object": "Finland"
        },
        {
            "subject": "Castleisland Desmonds GAA",
            "object": "Ireland"
        },
        {
            "subject": "Buchans",
            "object": "Canada"
        },
        {
            "subject": "Bungsberg",
            "object": "Germany"
        },
        {
            "subject": "Piazza al Serchio",
            "object": "Italy"
        },
        {
            "subject": "Bogra Zilla School",
            "object": "Bangladesh"
        },
        {
            "subject": "Ruhla",
            "object": "Germany"
        },
        {
            "subject": "Langarud County",
            "object": "Iran"
        },
        {
            "subject": "Bolvadin",
            "object": "Turkey"
        },
        {
            "subject": "Ufa",
            "object": "Russia"
        },
        {
            "subject": "Miramichi Centre",
            "object": "Canada"
        },
        {
            "subject": "Ulpiana",
            "object": "Kosovo"
        },
        {
            "subject": "L'Escala",
            "object": "Spain"
        },
        {
            "subject": "Hohenlohe",
            "object": "Germany"
        },
        {
            "subject": "Bunda District",
            "object": "Tanzania"
        },
        {
            "subject": "Mbale District",
            "object": "Uganda"
        },
        {
            "subject": "Habitat 67",
            "object": "Canada"
        },
        {
            "subject": "Eupen-Malmedy",
            "object": "Belgium"
        },
        {
            "subject": "Hrtkovci",
            "object": "Croatia"
        },
        {
            "subject": "SooToday.com",
            "object": "Canada"
        },
        {
            "subject": "CNH Industrial",
            "object": "Netherlands"
        },
        {
            "subject": "Nishi-Matsuura District",
            "object": "Japan"
        },
        {
            "subject": "Moscato d'Asti",
            "object": "Italy"
        },
        {
            "subject": "Namba Station",
            "object": "Japan"
        },
        {
            "subject": "Sands of Beirut",
            "object": "Lebanon"
        },
        {
            "subject": "Uda District",
            "object": "Japan"
        },
        {
            "subject": "Sabratha",
            "object": "Libya"
        },
        {
            "subject": "Free National Movement",
            "object": "Bahamas"
        },
        {
            "subject": "Shoranur",
            "object": "India"
        },
        {
            "subject": "Komarichsky District",
            "object": "Russia"
        },
        {
            "subject": "Niederweningen",
            "object": "Switzerland"
        },
        {
            "subject": "Tarnobrzeg Voivodeship",
            "object": "Poland"
        },
        {
            "subject": "Wabush Airport",
            "object": "Canada"
        },
        {
            "subject": "Fairfield West",
            "object": "Australia"
        },
        {
            "subject": "Lahti",
            "object": "Finland"
        },
        {
            "subject": "Kitakami Station",
            "object": "Japan"
        },
        {
            "subject": "Vaujany",
            "object": "France"
        },
        {
            "subject": "Tartessos",
            "object": "Spain"
        },
        {
            "subject": "Vinkeveen",
            "object": "Netherlands"
        },
        {
            "subject": "Asian Highway Network",
            "object": "India"
        },
        {
            "subject": "University of Zaragoza",
            "object": "Spain"
        },
        {
            "subject": "Breege",
            "object": "Germany"
        },
        {
            "subject": "Beneden Merwede",
            "object": "Netherlands"
        },
        {
            "subject": "Prieto Diaz",
            "object": "Philippines"
        },
        {
            "subject": "Saint-Louis-de-Kent, New Brunswick",
            "object": "Canada"
        },
        {
            "subject": "Hitachinaka",
            "object": "Japan"
        },
        {
            "subject": "Villa La Pietra",
            "object": "Italy"
        },
        {
            "subject": "Papanasam",
            "object": "India"
        },
        {
            "subject": "Capoeira",
            "object": "Brazil"
        },
        {
            "subject": "Strait of Kerch",
            "object": "Russia"
        },
        {
            "subject": "Big Timothy Mountain",
            "object": "Canada"
        },
        {
            "subject": "Bolpur",
            "object": "India"
        },
        {
            "subject": "Geelong Ring Road",
            "object": "Australia"
        },
        {
            "subject": "Mosque of Uqba",
            "object": "Tunisia"
        },
        {
            "subject": "Pinosava",
            "object": "Serbia"
        },
        {
            "subject": "Mezhdurechensky District",
            "object": "Russia"
        },
        {
            "subject": "Eurostat",
            "object": "Luxembourg"
        },
        {
            "subject": "Kharga Oasis",
            "object": "Egypt"
        },
        {
            "subject": "Gmina Pokrzywnica",
            "object": "Poland"
        },
        {
            "subject": "Fischenthal",
            "object": "Switzerland"
        },
        {
            "subject": "Parippally",
            "object": "India"
        },
        {
            "subject": "Fawkner",
            "object": "Australia"
        },
        {
            "subject": "Didymoteicho",
            "object": "Greece"
        },
        {
            "subject": "Transylvanian Plateau",
            "object": "Romania"
        },
        {
            "subject": "Gmina Warlubie",
            "object": "Poland"
        },
        {
            "subject": "New Era University",
            "object": "Philippines"
        },
        {
            "subject": "Kojur District",
            "object": "Iran"
        },
        {
            "subject": "Istanbul Airport",
            "object": "Turkey"
        },
        {
            "subject": "Tell Rifaat",
            "object": "Syria"
        },
        {
            "subject": "Warsaw Uprising Museum",
            "object": "Poland"
        },
        {
            "subject": "Ginza Line",
            "object": "Japan"
        },
        {
            "subject": "Landskrona BoIS",
            "object": "Sweden"
        },
        {
            "subject": "Queens Gardens, Brisbane",
            "object": "Australia"
        },
        {
            "subject": "Noyon",
            "object": "France"
        },
        {
            "subject": "Facit",
            "object": "Sweden"
        },
        {
            "subject": "Perpignan",
            "object": "France"
        },
        {
            "subject": "Beles River",
            "object": "Ethiopia"
        },
        {
            "subject": "Atromitos Piraeus F.C.",
            "object": "Greece"
        },
        {
            "subject": "Dewa Province",
            "object": "Japan"
        },
        {
            "subject": "Bilecik Province",
            "object": "Turkey"
        },
        {
            "subject": "Sebatik Island",
            "object": "Malaysia"
        },
        {
            "subject": "Grimaldi Industri",
            "object": "Sweden"
        },
        {
            "subject": "Ambatofinandrahana District",
            "object": "Madagascar"
        },
        {
            "subject": "Sarnia",
            "object": "Canada"
        },
        {
            "subject": "Suwayq",
            "object": "Oman"
        },
        {
            "subject": "South East Cape",
            "object": "Australia"
        },
        {
            "subject": "Abbey of Echternach",
            "object": "Luxembourg"
        },
        {
            "subject": "N-340 road",
            "object": "Spain"
        },
        {
            "subject": "European Physical Society",
            "object": "France"
        },
        {
            "subject": "Band-e Kaisar",
            "object": "Iran"
        },
        {
            "subject": "Jiul de Vest River",
            "object": "Romania"
        },
        {
            "subject": "Dziemiany",
            "object": "Poland"
        },
        {
            "subject": "Valvasone",
            "object": "Italy"
        },
        {
            "subject": "Mewat",
            "object": "India"
        },
        {
            "subject": "Koriya district",
            "object": "India"
        },
        {
            "subject": "Scheibbs District",
            "object": "Austria"
        },
        {
            "subject": "Birendranagar",
            "object": "Nepal"
        },
        {
            "subject": "Kondotty",
            "object": "India"
        },
        {
            "subject": "Logatec",
            "object": "Slovenia"
        },
        {
            "subject": "Toulouges",
            "object": "France"
        },
        {
            "subject": "Puerto Maldonado",
            "object": "Peru"
        },
        {
            "subject": "Boinpalle mandal",
            "object": "India"
        },
        {
            "subject": "Everberg",
            "object": "Belgium"
        },
        {
            "subject": "Novokuybyshevsk",
            "object": "Russia"
        },
        {
            "subject": "City of Cranbourne",
            "object": "Australia"
        },
        {
            "subject": "Adare Manor",
            "object": "Ireland"
        },
        {
            "subject": "Cmolas",
            "object": "Poland"
        },
        {
            "subject": "Flieden",
            "object": "Germany"
        },
        {
            "subject": "North Middlesex, Ontario",
            "object": "Canada"
        },
        {
            "subject": "Frasnes-lez-Anvaing",
            "object": "Belgium"
        },
        {
            "subject": "Lamongan",
            "object": "Indonesia"
        },
        {
            "subject": "Gulf of Bothnia",
            "object": "Finland"
        },
        {
            "subject": "Penna Ahobilam",
            "object": "India"
        },
        {
            "subject": "Party for Freedom",
            "object": "Netherlands"
        },
        {
            "subject": "Santa Cruz de Mompox",
            "object": "Colombia"
        },
        {
            "subject": "Teatro Comunale Florence",
            "object": "Italy"
        },
        {
            "subject": "Skole Raion",
            "object": "Ukraine"
        },
        {
            "subject": "County Carlow",
            "object": "Ireland"
        },
        {
            "subject": "Universidad Nacional Federico Villarreal",
            "object": "Peru"
        },
        {
            "subject": "Mumiy Troll",
            "object": "Russia"
        },
        {
            "subject": "Vukov Spomenik",
            "object": "Serbia"
        },
        {
            "subject": "Tillya Tepe",
            "object": "Afghanistan"
        },
        {
            "subject": "Presbyterian High School",
            "object": "Singapore"
        },
        {
            "subject": "Danish Sign Language",
            "object": "Denmark"
        },
        {
            "subject": "Lodhran Tehsil",
            "object": "Pakistan"
        },
        {
            "subject": "Linimo",
            "object": "Japan"
        },
        {
            "subject": "Surat Basin",
            "object": "Australia"
        },
        {
            "subject": "Expo 86",
            "object": "Canada"
        },
        {
            "subject": "Eriksbergs Mekaniska Verkstad",
            "object": "Sweden"
        },
        {
            "subject": "Foothills-Rocky View",
            "object": "Canada"
        },
        {
            "subject": "Chaville",
            "object": "France"
        },
        {
            "subject": "Lannemezan",
            "object": "France"
        },
        {
            "subject": "Asian Highway Network",
            "object": "Turkey"
        },
        {
            "subject": "Guggenheim Museum",
            "object": "Spain"
        },
        {
            "subject": "ERT World",
            "object": "Greece"
        },
        {
            "subject": "Manyakheta",
            "object": "India"
        },
        {
            "subject": "Tsubaki Grand Shrine",
            "object": "Japan"
        },
        {
            "subject": "Madala",
            "object": "India"
        },
        {
            "subject": "Garabit viaduct",
            "object": "France"
        },
        {
            "subject": "Alouette Lake",
            "object": "Canada"
        },
        {
            "subject": "Democrats 66",
            "object": "Netherlands"
        },
        {
            "subject": "Rathen",
            "object": "Germany"
        },
        {
            "subject": "Hornnes",
            "object": "Norway"
        },
        {
            "subject": "Lerik District",
            "object": "Azerbaijan"
        },
        {
            "subject": "Buda",
            "object": "Hungary"
        },
        {
            "subject": "Waldshut-Tiengen",
            "object": "Germany"
        },
        {
            "subject": "Les Bons Villers",
            "object": "Belgium"
        },
        {
            "subject": "Askola",
            "object": "Finland"
        },
        {
            "subject": "Wellington Island",
            "object": "Chile"
        },
        {
            "subject": "Hobart Zoo",
            "object": "Australia"
        },
        {
            "subject": "Kume District",
            "object": "Japan"
        },
        {
            "subject": "Simdega",
            "object": "India"
        },
        {
            "subject": "Yadagirigutta Temple",
            "object": "India"
        },
        {
            "subject": "Honnavar",
            "object": "India"
        },
        {
            "subject": "Romano d'Ezzelino",
            "object": "Italy"
        },
        {
            "subject": "La famille Plouffe",
            "object": "Canada"
        },
        {
            "subject": "Buchan",
            "object": "Australia"
        },
        {
            "subject": "ITE College East",
            "object": "Singapore"
        },
        {
            "subject": "Munich",
            "object": "Germany"
        },
        {
            "subject": "Bearpaw Shale",
            "object": "Canada"
        },
        {
            "subject": "Little Stirrup Cay",
            "object": "Bahamas"
        },
        {
            "subject": "Tampere Cathedral",
            "object": "Finland"
        },
        {
            "subject": "Tudeshk Rural District",
            "object": "Iran"
        },
        {
            "subject": "Sonitpur district",
            "object": "India"
        },
        {
            "subject": "Chancelade",
            "object": "France"
        },
        {
            "subject": "Boguchany Dam",
            "object": "Russia"
        },
        {
            "subject": "Veysian Rural District",
            "object": "Iran"
        },
        {
            "subject": ".af",
            "object": "Afghanistan"
        },
        {
            "subject": "Argentine National Anthem",
            "object": "Argentina"
        },
        {
            "subject": "Hagenow",
            "object": "Germany"
        },
        {
            "subject": "La Guajira Desert",
            "object": "Colombia"
        },
        {
            "subject": "Santa Maria da Feira Municipality",
            "object": "Portugal"
        },
        {
            "subject": "Helmbrechts",
            "object": "Germany"
        },
        {
            "subject": "La Ribera Baixa",
            "object": "Spain"
        },
        {
            "subject": "Canton of Schaffhausen",
            "object": "Switzerland"
        },
        {
            "subject": "AMK Hub",
            "object": "Singapore"
        },
        {
            "subject": "Taronga Western Plains Zoo",
            "object": "Australia"
        },
        {
            "subject": "Melaka TMFC",
            "object": "Malaysia"
        },
        {
            "subject": "regiopolis",
            "object": "Germany"
        },
        {
            "subject": "Gio Linh",
            "object": "Vietnam"
        },
        {
            "subject": "Swedish Orphan Biovitrum",
            "object": "Sweden"
        },
        {
            "subject": "Ovada",
            "object": "Italy"
        },
        {
            "subject": "Zelenchukskaya",
            "object": "Russia"
        },
        {
            "subject": "Tsuno District, Yamaguchi",
            "object": "Japan"
        },
        {
            "subject": "Valdichiana",
            "object": "Italy"
        },
        {
            "subject": "Kazinga Channel",
            "object": "Uganda"
        },
        {
            "subject": "Columbia Valley",
            "object": "Canada"
        },
        {
            "subject": "Iraklis F.C.",
            "object": "Greece"
        },
        {
            "subject": "Wazzin",
            "object": "Libya"
        },
        {
            "subject": "Tiv people",
            "object": "Nigeria"
        },
        {
            "subject": "Cubagua",
            "object": "Venezuela"
        },
        {
            "subject": "Nobel Peace Center",
            "object": "Norway"
        },
        {
            "subject": "Addanki mandal",
            "object": "India"
        },
        {
            "subject": "Foundation for a Free Information Infrastructure",
            "object": "Germany"
        },
        {
            "subject": "Frosinone",
            "object": "Italy"
        },
        {
            "subject": "Simcoe Composite School",
            "object": "Canada"
        },
        {
            "subject": "Chol Kiri District",
            "object": "Cambodia"
        },
        {
            "subject": "Plougonven",
            "object": "France"
        },
        {
            "subject": "National Congress of Brasil",
            "object": "Brazil"
        },
        {
            "subject": "Piedecuesta",
            "object": "Colombia"
        },
        {
            "subject": "Khorramdarreh Rural District",
            "object": "Iran"
        },
        {
            "subject": "Gjerpen",
            "object": "Norway"
        },
        {
            "subject": "Schleitheim",
            "object": "Switzerland"
        },
        {
            "subject": "Mont Saint-Bruno",
            "object": "Canada"
        },
        {
            "subject": "Thiruvattar",
            "object": "India"
        },
        {
            "subject": "Erbil SC",
            "object": "Iraq"
        },
        {
            "subject": "Holycross-Ballycahill GAA",
            "object": "Ireland"
        },
        {
            "subject": "AH3",
            "object": "Russia"
        },
        {
            "subject": "Guelma Province",
            "object": "Algeria"
        },
        {
            "subject": "Laslea",
            "object": "Romania"
        },
        {
            "subject": "Ogrodzieniec",
            "object": "Poland"
        },
        {
            "subject": "Christian Democrats",
            "object": "Finland"
        },
        {
            "subject": "Teshie",
            "object": "Ghana"
        },
        {
            "subject": "Southern Savonia",
            "object": "Finland"
        },
        {
            "subject": "Holmenkollen National Arena",
            "object": "Norway"
        },
        {
            "subject": "Tirebolu",
            "object": "Turkey"
        },
        {
            "subject": "Ghora Gali",
            "object": "Pakistan"
        },
        {
            "subject": "Bedourie",
            "object": "Australia"
        },
        {
            "subject": "Urangan",
            "object": "Australia"
        },
        {
            "subject": "Hadzhidimovo",
            "object": "Bulgaria"
        },
        {
            "subject": "Villars-Burquin",
            "object": "Switzerland"
        },
        {
            "subject": "Berar Province",
            "object": "India"
        },
        {
            "subject": "Avord",
            "object": "France"
        },
        {
            "subject": "Montreal Centre",
            "object": "Canada"
        },
        {
            "subject": "Singarapettai",
            "object": "India"
        },
        {
            "subject": "Carpathian Mountains",
            "object": "Austria"
        },
        {
            "subject": "Hilir Perak",
            "object": "Malaysia"
        },
        {
            "subject": "Sardent",
            "object": "France"
        },
        {
            "subject": "Vernayaz",
            "object": "Switzerland"
        },
        {
            "subject": "Gmina Sorkwity",
            "object": "Poland"
        },
        {
            "subject": "Sulaimaniyah International Airport",
            "object": "Iraq"
        },
        {
            "subject": "Shibganj Upazila, Bogra District",
            "object": "Bangladesh"
        },
        {
            "subject": "Pacentro",
            "object": "Italy"
        },
        {
            "subject": "Entracque",
            "object": "Italy"
        },
        {
            "subject": "Castellamonte",
            "object": "Italy"
        },
        {
            "subject": "Borghetto di Vara",
            "object": "Italy"
        },
        {
            "subject": "War in Donbass",
            "object": "Ukraine"
        },
        {
            "subject": "Iruma Air Base",
            "object": "Japan"
        },
        {
            "subject": "Nkawkaw",
            "object": "Ghana"
        },
        {
            "subject": "Sialkot district",
            "object": "Pakistan"
        },
        {
            "subject": "Montiel",
            "object": "Spain"
        },
        {
            "subject": "Public Broadcasting Services",
            "object": "Malta"
        },
        {
            "subject": "Ponoy River",
            "object": "Russia"
        },
        {
            "subject": "Catalonia",
            "object": "Spain"
        },
        {
            "subject": "Baron de Hirsch Cemetery, Halifax",
            "object": "Canada"
        },
        {
            "subject": "Jervis Inlet",
            "object": "Canada"
        },
        {
            "subject": "Hersbruck",
            "object": "Germany"
        },
        {
            "subject": "Turaida",
            "object": "Latvia"
        },
        {
            "subject": "Marstrand",
            "object": "Sweden"
        },
        {
            "subject": "Brandon University",
            "object": "Canada"
        },
        {
            "subject": "Windischeschenbach",
            "object": "Germany"
        },
        {
            "subject": "Langtang National Park",
            "object": "Nepal"
        },
        {
            "subject": "Porto Azzurro",
            "object": "Italy"
        },
        {
            "subject": "Ariake Coliseum",
            "object": "Japan"
        },
        {
            "subject": "Jonava District Municipality",
            "object": "Lithuania"
        },
        {
            "subject": "Albertis Castle",
            "object": "Italy"
        },
        {
            "subject": "Thamshavn Line",
            "object": "Norway"
        },
        {
            "subject": "Abu Ghosh",
            "object": "Israel"
        },
        {
            "subject": "K.S.V. Roeselare",
            "object": "Belgium"
        },
        {
            "subject": "Kings Domain",
            "object": "Australia"
        },
        {
            "subject": "Kolad",
            "object": "India"
        },
        {
            "subject": "Ruthweiler",
            "object": "Germany"
        },
        {
            "subject": "Neighbourhoods in Kolkata",
            "object": "India"
        },
        {
            "subject": "Vardasht Rural District",
            "object": "Iran"
        },
        {
            "subject": "Eurasian Steppe",
            "object": "Ukraine"
        },
        {
            "subject": "public transport in Istanbul",
            "object": "Turkey"
        },
        {
            "subject": "Wentworth Valley",
            "object": "Canada"
        },
        {
            "subject": "Prince Edward Viaduct",
            "object": "Canada"
        },
        {
            "subject": "Kapar",
            "object": "Malaysia"
        },
        {
            "subject": "Autonomous District Lok Sabha constituency",
            "object": "India"
        },
        {
            "subject": "Pandoh Dam",
            "object": "India"
        },
        {
            "subject": "route 75",
            "object": "Australia"
        },
        {
            "subject": "Now Kandeh District",
            "object": "Iran"
        },
        {
            "subject": "Augustinergasse",
            "object": "Switzerland"
        },
        {
            "subject": "Vrienden van het Platteland",
            "object": "Netherlands"
        },
        {
            "subject": "Kresttsy",
            "object": "Russia"
        },
        {
            "subject": "Minamiarupusu",
            "object": "Japan"
        },
        {
            "subject": "Hotel Oloffson",
            "object": "Haiti"
        },
        {
            "subject": "Staatliche Antikensammlungen",
            "object": "Germany"
        },
        {
            "subject": "Madona District",
            "object": "Latvia"
        },
        {
            "subject": "Gmina Morawica",
            "object": "Poland"
        },
        {
            "subject": "Pamukkale",
            "object": "Turkey"
        },
        {
            "subject": "Prachin Buri River",
            "object": "Thailand"
        },
        {
            "subject": "2010 Belgian federal election",
            "object": "Belgium"
        },
        {
            "subject": "Himmelbjerget",
            "object": "Denmark"
        },
        {
            "subject": "prefectural road",
            "object": "Japan"
        },
        {
            "subject": "Kafriya",
            "object": "Syria"
        },
        {
            "subject": "Temples of Abu Simbel",
            "object": "Egypt"
        },
        {
            "subject": "Croom, County Limerick",
            "object": "Ireland"
        },
        {
            "subject": "Hammarby IF DFF",
            "object": "Sweden"
        },
        {
            "subject": "Putyvl",
            "object": "Ukraine"
        },
        {
            "subject": "Passeier Valley",
            "object": "Italy"
        },
        {
            "subject": "Sanlih E-Television",
            "object": "Taiwan"
        },
        {
            "subject": "Beckingen",
            "object": "Germany"
        },
        {
            "subject": "Whiteshell Laboratories",
            "object": "Canada"
        },
        {
            "subject": "Issenheim",
            "object": "France"
        },
        {
            "subject": "Western Bug",
            "object": "Belarus"
        },
        {
            "subject": "Maella",
            "object": "Spain"
        },
        {
            "subject": "Villigen",
            "object": "Switzerland"
        },
        {
            "subject": "Pazhayangadi",
            "object": "India"
        },
        {
            "subject": "Nyeri County",
            "object": "Kenya"
        },
        {
            "subject": "Spanish Armed Forces",
            "object": "Spain"
        },
        {
            "subject": "Capdenac",
            "object": "France"
        },
        {
            "subject": "Santo Spirito in Sassia",
            "object": "Italy"
        },
        {
            "subject": "Isla Grande de Tierra del Fuego",
            "object": "Argentina"
        },
        {
            "subject": "Tovuz District",
            "object": "Azerbaijan"
        },
        {
            "subject": "Periyar University",
            "object": "India"
        },
        {
            "subject": "Bispebjerg",
            "object": "Denmark"
        },
        {
            "subject": "Nintendo",
            "object": "Japan"
        },
        {
            "subject": "Blennerville",
            "object": "Ireland"
        },
        {
            "subject": "Fort Madalena",
            "object": "Malta"
        },
        {
            "subject": "All-Ukrainian Union \"Svoboda\"",
            "object": "Ukraine"
        },
        {
            "subject": "Campeche Bank",
            "object": "Mexico"
        },
        {
            "subject": "Lauterecken-Wolfstein",
            "object": "Germany"
        },
        {
            "subject": "Maison du Peuple",
            "object": "Belgium"
        },
        {
            "subject": "Panagarh",
            "object": "India"
        },
        {
            "subject": "Gobind Sagar",
            "object": "India"
        },
        {
            "subject": "Gobardanga",
            "object": "India"
        },
        {
            "subject": "AA Drink-leontien.nl",
            "object": "Netherlands"
        },
        {
            "subject": "Saint Gayane Church",
            "object": "Armenia"
        },
        {
            "subject": "Bose Institute",
            "object": "India"
        },
        {
            "subject": "Naumburg (Saale)",
            "object": "Germany"
        },
        {
            "subject": "Balige",
            "object": "Indonesia"
        },
        {
            "subject": "Panna National Park",
            "object": "India"
        },
        {
            "subject": "Garbeta",
            "object": "India"
        },
        {
            "subject": "2004 IAAF World Cross Country Championships",
            "object": "Belgium"
        },
        {
            "subject": "Gurudwara Bangla Sahib",
            "object": "India"
        },
        {
            "subject": "Hispaniola",
            "object": "Haiti"
        },
        {
            "subject": "Rock al Parque",
            "object": "Colombia"
        },
        {
            "subject": "Vermilion",
            "object": "Canada"
        },
        {
            "subject": "Isola Dovarese",
            "object": "Italy"
        },
        {
            "subject": "Castrovirreyna District",
            "object": "Peru"
        },
        {
            "subject": "Colombes",
            "object": "France"
        },
        {
            "subject": "The Forks, Winnipeg",
            "object": "Canada"
        },
        {
            "subject": "Mandailing language",
            "object": "Indonesia"
        },
        {
            "subject": "Tovarnik",
            "object": "Croatia"
        },
        {
            "subject": "Wakefield Park",
            "object": "Australia"
        },
        {
            "subject": "Nesodden IF",
            "object": "Norway"
        },
        {
            "subject": "Alcanena Municipality",
            "object": "Portugal"
        },
        {
            "subject": "Babcock & Brown",
            "object": "Australia"
        },
        {
            "subject": "Persegres Gresik United",
            "object": "Indonesia"
        },
        {
            "subject": "Opel",
            "object": "Germany"
        },
        {
            "subject": "Orikhiv",
            "object": "Ukraine"
        },
        {
            "subject": "Kamchatka Krai",
            "object": "Russia"
        },
        {
            "subject": "Grianan of Aileach",
            "object": "Ireland"
        },
        {
            "subject": "Cairo American College",
            "object": "Egypt"
        },
        {
            "subject": "East Karelia",
            "object": "Russia"
        },
        {
            "subject": "Siquijor",
            "object": "Philippines"
        },
        {
            "subject": "Mukhed",
            "object": "India"
        },
        {
            "subject": "Katwijk aan den Rijn",
            "object": "Netherlands"
        },
        {
            "subject": "Chartered Professional Accountant",
            "object": "Canada"
        },
        {
            "subject": "College of Engineering, Pune",
            "object": "India"
        },
        {
            "subject": "VR warehouses",
            "object": "Finland"
        },
        {
            "subject": "Tartu Town Hall",
            "object": "Estonia"
        },
        {
            "subject": "Palupera Rural Municipality",
            "object": "Estonia"
        },
        {
            "subject": "Bamyan",
            "object": "Afghanistan"
        },
        {
            "subject": "Gaiola",
            "object": "Italy"
        },
        {
            "subject": "West Royalty, Prince Edward Island",
            "object": "Canada"
        },
        {
            "subject": "Northern Territory",
            "object": "Australia"
        },
        {
            "subject": "Monarcas Morelia",
            "object": "Mexico"
        },
        {
            "subject": "Leiria",
            "object": "Portugal"
        },
        {
            "subject": "Taunsa Barrage",
            "object": "Pakistan"
        },
        {
            "subject": "Pully",
            "object": "Switzerland"
        },
        {
            "subject": "Jemappes",
            "object": "Belgium"
        },
        {
            "subject": "Gmina Olsztyn",
            "object": "Poland"
        },
        {
            "subject": "2009 Speedway Ekstraliga",
            "object": "Poland"
        },
        {
            "subject": "Taranto Sport",
            "object": "Italy"
        },
        {
            "subject": "Nea Zichni Municipality",
            "object": "Greece"
        },
        {
            "subject": "Louth County Council",
            "object": "Ireland"
        },
        {
            "subject": "Mannheim City Airport",
            "object": "Germany"
        },
        {
            "subject": "Le Fuilet",
            "object": "France"
        },
        {
            "subject": "Castlehaven",
            "object": "Ireland"
        },
        {
            "subject": "Kowsar County",
            "object": "Iran"
        },
        {
            "subject": "Dunnamaggin GAA",
            "object": "Ireland"
        },
        {
            "subject": "Fukuno, Toyama",
            "object": "Japan"
        },
        {
            "subject": "Isfahan International Airport",
            "object": "Iran"
        },
        {
            "subject": "Gasunie",
            "object": "Netherlands"
        },
        {
            "subject": "Garkan Rural District",
            "object": "Iran"
        },
        {
            "subject": "Treuchtlingen",
            "object": "Germany"
        },
        {
            "subject": "Minu District",
            "object": "Iran"
        },
        {
            "subject": "West Darfur",
            "object": "Sudan"
        },
        {
            "subject": "Kuomintang",
            "object": "Taiwan"
        },
        {
            "subject": "Casiquiare canal",
            "object": "Venezuela"
        },
        {
            "subject": "Electoral district of Wantirna",
            "object": "Australia"
        },
        {
            "subject": "Tesco Organisation",
            "object": "Germany"
        },
        {
            "subject": "Tarq Rud Rural District",
            "object": "Iran"
        },
        {
            "subject": "Rottendorf",
            "object": "Germany"
        },
        {
            "subject": "CFMJ",
            "object": "Canada"
        },
        {
            "subject": "Mahur Berenji Rural District",
            "object": "Iran"
        },
        {
            "subject": "Sydney Sports Ground",
            "object": "Australia"
        },
        {
            "subject": "Gmina Konarzyny",
            "object": "Poland"
        },
        {
            "subject": "Ichchapuram",
            "object": "India"
        },
        {
            "subject": "Hogeschool Gent",
            "object": "Belgium"
        },
        {
            "subject": "Aventine Hill",
            "object": "Italy"
        },
        {
            "subject": "plaza de Cibeles",
            "object": "Spain"
        },
        {
            "subject": "Fluminense F.C.",
            "object": "Brazil"
        },
        {
            "subject": "Hantsavichy",
            "object": "Belarus"
        },
        {
            "subject": "Dornbirn",
            "object": "Austria"
        },
        {
            "subject": "Berhala Island, Sabah",
            "object": "Malaysia"
        },
        {
            "subject": "St Lucia",
            "object": "Australia"
        },
        {
            "subject": "Ghatanji",
            "object": "India"
        },
        {
            "subject": "FC Volochanin-Ratmir Vyshny Volochyok",
            "object": "Russia"
        },
        {
            "subject": "Party of National Unity",
            "object": "Kenya"
        },
        {
            "subject": "Oshawa",
            "object": "Canada"
        },
        {
            "subject": "Ledaal",
            "object": "Norway"
        },
        {
            "subject": "Lewin Brzeski",
            "object": "Poland"
        },
        {
            "subject": "Tampines Expressway",
            "object": "Singapore"
        },
        {
            "subject": "Menen",
            "object": "Belgium"
        },
        {
            "subject": "Fryderyk Chopin University of Music",
            "object": "Poland"
        },
        {
            "subject": "Ikuno-ku",
            "object": "Japan"
        },
        {
            "subject": "Velbert",
            "object": "Germany"
        },
        {
            "subject": "Olten railway station",
            "object": "Switzerland"
        },
        {
            "subject": "SV Ried",
            "object": "Austria"
        },
        {
            "subject": "Greater Rio de Janeiro",
            "object": "Brazil"
        },
        {
            "subject": "Ulundurpet",
            "object": "India"
        },
        {
            "subject": "Eerbeek",
            "object": "Netherlands"
        },
        {
            "subject": "Nimmitabel",
            "object": "Australia"
        },
        {
            "subject": "Cenepa River",
            "object": "Peru"
        },
        {
            "subject": "Biberach district",
            "object": "Germany"
        },
        {
            "subject": "Bad Wildungen",
            "object": "Germany"
        },
        {
            "subject": "Minamiakita District",
            "object": "Japan"
        },
        {
            "subject": "TROS",
            "object": "Netherlands"
        },
        {
            "subject": "Haut Atlas",
            "object": "Morocco"
        },
        {
            "subject": "Moissac Abbey",
            "object": "France"
        },
        {
            "subject": "Tempi Municipality",
            "object": "Greece"
        },
        {
            "subject": "Steenwijk",
            "object": "Netherlands"
        },
        {
            "subject": "Khmilnyk",
            "object": "Ukraine"
        },
        {
            "subject": "Lascaris Battery",
            "object": "Malta"
        },
        {
            "subject": "Instituto Pedro Nunes",
            "object": "Portugal"
        },
        {
            "subject": "Grolsch Brewery",
            "object": "Netherlands"
        },
        {
            "subject": "Alpokalja",
            "object": "Hungary"
        },
        {
            "subject": "New Democratic Party Socialist Caucus",
            "object": "Canada"
        },
        {
            "subject": "Pragersko",
            "object": "Slovenia"
        },
        {
            "subject": "Preet Vihar",
            "object": "India"
        },
        {
            "subject": "Ausa",
            "object": "India"
        },
        {
            "subject": "Larsmo",
            "object": "Finland"
        },
        {
            "subject": "Manikata",
            "object": "Malta"
        },
        {
            "subject": "archdiocese of Gatineau",
            "object": "Canada"
        },
        {
            "subject": "Indira Gandhi International Airport",
            "object": "India"
        },
        {
            "subject": "Dundalk",
            "object": "Ireland"
        },
        {
            "subject": "Waurn Ponds",
            "object": "Australia"
        },
        {
            "subject": "IJmuiden",
            "object": "Netherlands"
        },
        {
            "subject": "Milltown Institute of Theology and Philosophy",
            "object": "Ireland"
        },
        {
            "subject": "Cappoquin",
            "object": "Ireland"
        },
        {
            "subject": "Mukkam",
            "object": "India"
        },
        {
            "subject": "Mugello Circuit",
            "object": "Italy"
        },
        {
            "subject": "bpost",
            "object": "Belgium"
        },
        {
            "subject": "Sana'a International Airport",
            "object": "Yemen"
        },
        {
            "subject": "Enghien-les-Bains",
            "object": "France"
        },
        {
            "subject": "Lajran Rural District",
            "object": "Iran"
        },
        {
            "subject": "Geffen Award",
            "object": "Israel"
        },
        {
            "subject": "Halton County, Ontario",
            "object": "Canada"
        },
        {
            "subject": "Shire of Wambo",
            "object": "Australia"
        },
        {
            "subject": "St James' Church, Sydney",
            "object": "Australia"
        },
        {
            "subject": "Hamilton Mountain",
            "object": "Canada"
        },
        {
            "subject": "Badoc",
            "object": "Philippines"
        },
        {
            "subject": "Oder-Spree District",
            "object": "Germany"
        },
        {
            "subject": "Vesuvius Observatory",
            "object": "Italy"
        },
        {
            "subject": "Col Agnel",
            "object": "Italy"
        },
        {
            "subject": "Catholic Syrian Bank",
            "object": "India"
        },
        {
            "subject": "Anak Bukit",
            "object": "Malaysia"
        },
        {
            "subject": "Welschnofen",
            "object": "Italy"
        },
        {
            "subject": "Kretinga",
            "object": "Lithuania"
        },
        {
            "subject": "Lipscani",
            "object": "Romania"
        },
        {
            "subject": "Emscher",
            "object": "Germany"
        },
        {
            "subject": "Morshi",
            "object": "India"
        },
        {
            "subject": "Wiener Singakademie",
            "object": "Austria"
        },
        {
            "subject": "Baturyn",
            "object": "Ukraine"
        },
        {
            "subject": "Hida Mountains",
            "object": "Japan"
        },
        {
            "subject": "Shastri Park",
            "object": "India"
        },
        {
            "subject": "Grand Mosque of Paris",
            "object": "France"
        },
        {
            "subject": "Llanquihue Province",
            "object": "Chile"
        },
        {
            "subject": "Zuiderzee",
            "object": "Netherlands"
        },
        {
            "subject": "Illertissen",
            "object": "Germany"
        },
        {
            "subject": "KBC Bank",
            "object": "Belgium"
        },
        {
            "subject": "Soalala District",
            "object": "Madagascar"
        },
        {
            "subject": "Yamato Museum",
            "object": "Japan"
        },
        {
            "subject": "Valea lui Mihai",
            "object": "Romania"
        },
        {
            "subject": "Central Black Forest",
            "object": "Germany"
        },
        {
            "subject": "Selbu",
            "object": "Norway"
        },
        {
            "subject": "Sahneh County",
            "object": "Iran"
        },
        {
            "subject": "Legnica County",
            "object": "Poland"
        },
        {
            "subject": "Al Ahmadi Governorate",
            "object": "Kuwait"
        },
        {
            "subject": "Gmina Kleczew",
            "object": "Poland"
        },
        {
            "subject": "Allan Cup",
            "object": "Canada"
        },
        {
            "subject": "Bukit Panjang Single Member Constituency",
            "object": "Singapore"
        },
        {
            "subject": "1C Company",
            "object": "Russia"
        },
        {
            "subject": "Kingston Whig-Standard",
            "object": "Canada"
        },
        {
            "subject": "University of Bern",
            "object": "Switzerland"
        },
        {
            "subject": "Palana",
            "object": "Russia"
        },
        {
            "subject": "Rudrur",
            "object": "India"
        },
        {
            "subject": "Tukvar Tea Estate",
            "object": "India"
        },
        {
            "subject": "Bastia",
            "object": "France"
        },
        {
            "subject": "Nauders",
            "object": "Austria"
        },
        {
            "subject": "Winlaton Youth Training Centre",
            "object": "Australia"
        },
        {
            "subject": "Glencree",
            "object": "Ireland"
        },
        {
            "subject": "Bzura",
            "object": "Poland"
        },
        {
            "subject": "Lake Timiskaming",
            "object": "Canada"
        },
        {
            "subject": "Emba River",
            "object": "Kazakhstan"
        },
        {
            "subject": "Bintulu Division",
            "object": "Malaysia"
        },
        {
            "subject": "Tatsuno",
            "object": "Japan"
        },
        {
            "subject": "Siemiatycze",
            "object": "Poland"
        },
        {
            "subject": "Pampilhosa da Serra",
            "object": "Portugal"
        },
        {
            "subject": "Ostermundigen",
            "object": "Switzerland"
        },
        {
            "subject": "Sabburah Subdistrict",
            "object": "Syria"
        },
        {
            "subject": "Desolation Lava Field",
            "object": "Canada"
        },
        {
            "subject": "Wallmerod",
            "object": "Germany"
        }
    ]
}